grizzs/__init__.py
grizzs-0.0.1.dist-info/METADATA
grizzs-0.0.1.dist-info/WHEEL
grizzs-0.0.1.dist-info/top_level.txt
grizzs-0.0.1.dist-info/RECORD
