Metadata-Version: 2.4
Name: grizzs
Version: 0.0.1
Summary: Experimental columnar data engine (placeholder)
Author-email: Grizzs <grizzs.py@gmail.com>
License: BSD-3-Clause
Classifier: Development Status :: 1 - Planning
Classifier: Programming Language :: Python :: 3
Classifier: License :: OSI Approved :: BSD License
Classifier: Intended Audience :: Developers
Requires-Python: >=3.9
